ckhCal/__init__.py
ckhCal/calculations.py
ckhCal-0.0.2.dist-info/METADATA
ckhCal-0.0.2.dist-info/WHEEL
ckhCal-0.0.2.dist-info/top_level.txt
ckhCal-0.0.2.dist-info/RECORD
