Metadata-Version: 2.1
Name: ckhCal
Version: 0.0.2
Summary: Calculation Package
Author: CKH
Author-email: cloud.ckhathri@gmail.com
Classifier: Programming Language :: Python :: 3
Classifier: License :: OSI Approved :: MIT License
Classifier: Operating System :: OS Independent
Requires-Python: >=3.6
